<alignment>
  <sentence>
    <word normalized="Rick">Rick </word>
    <word normalized="Rude">Rude </word>
    <word normalized="Richard">Richard </word>
    <word normalized="Erwin">Erwin </word>
    <word normalized="Rood">Rood </word>
    <word normalized="">(</word>
    <word normalized="December">December </word>
    <word normalized="seven">7 </word>
    <word normalized="nineteen">19 </word>
    <word normalized="hundred">hundred </word>
    <word normalized="fifty eight">58 </word>
    <word normalized="minus">– </word>
    <word normalized="April">April </word>
    <word normalized="twenty">20 </word>
    <word normalized="nineteen">19 </word>
    <word normalized="hundred">hundred </word>
    <word normalized="ninety nine">99</word>
    <word normalized="">)</word>
    <word normalized="">, </word>
    <word normalized="better">better </word>
    <word normalized="known">known </word>
    <word normalized="by">by </word>
    <word normalized="his">his </word>
    <word normalized="ring">ring </word>
    <word normalized="name">name </word>
    <word normalized="">"</word>
    <word normalized="Ravishing">Ravishing</word>
    <word normalized="">" </word>
    <word normalized="Rick">Rick </word>
    <word normalized="Rude">Rude</word>
    <word normalized="">, </word>
    <word normalized="was">was </word>
    <word normalized="a">a </word>
    <word normalized="professional">professional </word>
    <word normalized="wrestler">wrestler </word>
    <word normalized="who">who </word>
    <word normalized="performed">performed </word>
    <word normalized="for">for </word>
    <word normalized="many">many </word>
    <word normalized="promotions">promotions</word>
    <word normalized="">, </word>
    <word normalized="most">most </word>
    <word normalized="notably">notably </word>
    <word normalized="World">World </word>
    <word normalized="Championship">Championship </word>
    <word normalized="Wrestling">Wrestling </word>
    <word normalized="and">and </word>
    <word normalized="the">the </word>
    <word normalized="World">World </word>
    <word normalized="Wrestling">Wrestling </word>
    <word normalized="Federation">Federation</word>
    <word normalized="">, </word>
    <word normalized="in">in </word>
    <word normalized="the">the </word>
    <word normalized="19">19 </word>
    <word normalized="hundred">hundred </word>
    <word normalized="eighties">80s </word>
    <word normalized="and">and </word>
    <word normalized="nineteen">19 </word>
    <word normalized="hundred">hundred </word>
    <word normalized="nineties">90s</word>
    <word normalized="">. </word>
  </sentence>
  <sentence>
    <word normalized="He">He </word>
    <word normalized="was">was </word>
    <word normalized="a">a </word>
    <word normalized="two">two </word>
    <word normalized="time">time </word>
    <word normalized="WCWA">WCWA </word>
    <word normalized="Heavyweight">Heavyweight </word>
    <word normalized="Champion">Champion</word>
    <word normalized="">, </word>
    <word normalized="during">during </word>
    <word normalized="his">his </word>
    <word normalized="first">first </word>
    <word normalized="reign">reign </word>
    <word normalized="it">it </word>
    <word normalized="was">was </word>
    <word normalized="known">known </word>
    <word normalized="as">as </word>
    <word normalized="the">the </word>
    <word normalized="NWA">NWA </word>
    <word normalized="American">American </word>
    <word normalized="Heavyweight">Heavyweight </word>
    <word normalized="Championship">Championship</word>
    <word normalized="">. </word>
  </sentence>
  <sentence>
    <word normalized="Table">Table </word>
    <word normalized="of">of </word>
    <word normalized="contents">contents </word>
    <word normalized="Section">Section </word>
    <word normalized="one">1 </word>
    <word normalized="Career">Career </word>
    <word normalized="Born">Born </word>
    <word normalized="in">in </word>
    <word normalized="saint">St. </word>
    <word normalized="Peter">Peter</word>
    <word normalized="">, </word>
    <word normalized="Minnesota">Minnesota</word>
    <word normalized="">, </word>
    <word normalized="Rood">Rood </word>
    <word normalized="attended">attended </word>
    <word normalized="Robbinsdale">Robbinsdale </word>
    <word normalized="High">High </word>
    <word normalized="School">School </word>
    <word normalized="in">in </word>
    <word normalized="Robbinsdale">Robbinsdale</word>
    <word normalized="">, </word>
    <word normalized="Minnesota">Minnesota </word>
    <word normalized="with">with </word>
    <word normalized="Tom">Tom </word>
    <word normalized="Zenk">Zenk</word>
    <word normalized="">, </word>
    <word normalized="Brady">Brady </word>
    <word normalized="Boone">Boone</word>
    <word normalized="">, </word>
    <word normalized="Nikita">Nikita </word>
    <word normalized="Koloff">Koloff</word>
    <word normalized="">, </word>
    <word normalized="Curt">Curt </word>
    <word normalized="Hennig">Hennig</word>
    <word normalized="">, </word>
    <word normalized="John">John </word>
    <word normalized="Nord">Nord</word>
    <word normalized="">, </word>
    <word normalized="and">and </word>
    <word normalized="Barry">Barry </word>
    <word normalized="Darsow">Darsow</word>
    <word normalized="">, </word>
    <word normalized="all">all </word>
    <word normalized="of">of </word>
    <word normalized="whom">whom </word>
    <word normalized="later">later </word>
    <word normalized="became">became </word>
    <word normalized="professional">professional </word>
    <word normalized="wrestlers">wrestlers</word>
    <word normalized="">. </word>
  </sentence>
  <sentence>
    <word normalized="After">After </word>
    <word normalized="graduating">graduating </word>
    <word normalized="from">from </word>
    <word normalized="Anoka">Anoka </word>
    <word normalized="Ramsey">Ramsey </word>
    <word normalized="Junior">Junior </word>
    <word normalized="College">College </word>
    <word normalized="with">with </word>
    <word normalized="a">a </word>
    <word normalized="degree">degree </word>
    <word normalized="in">in </word>
    <word normalized="Physical">Physical </word>
    <word normalized="Education">Education</word>
    <word normalized="">, </word>
    <word normalized="Rood">Rood </word>
    <word normalized="began">began </word>
    <word normalized="wrestling">wrestling </word>
    <word normalized="in">in </word>
    <word normalized="nineteen">19 </word>
    <word normalized="hundred">hundred </word>
    <word normalized="eighty three">83 </word>
    <word normalized="as">as </word>
    <word normalized="Ricky">Ricky </word>
    <word normalized="Rood">Rood</word>
    <word normalized="">, </word>
    <word normalized="a">a </word>
    <word normalized="babyface">babyface </word>
    <word normalized="jobber">jobber</word>
    <word normalized="">. </word>
  </sentence>
  <sentence>
    <word normalized="He">He </word>
    <word normalized="started">started </word>
    <word normalized="with">with </word>
    <word normalized="Vancouver s">Vancouver's </word>
    <word normalized="NWA">NWA </word>
    <word normalized="All Star">All-Star </word>
    <word normalized="Wrestling">Wrestling </word>
    <word normalized="before">before </word>
    <word normalized="moving">moving </word>
    <word normalized="on">on </word>
    <word normalized="to">to </word>
    <word normalized="compete">compete </word>
    <word normalized="for">for </word>
    <word normalized="Georgia">Georgia </word>
    <word normalized="Championship">Championship </word>
    <word normalized="Wrestling">Wrestling </word>
    <word normalized="and">and </word>
    <word normalized="later">later </word>
    <word normalized="Memphis based">Memphis-based </word>
    <word normalized="Mid Southern">Mid-Southern </word>
    <word normalized="Wrestling">Wrestling</word>
    <word normalized="">. </word>
  </sentence>
  <sentence>
    <word normalized="He">He </word>
    <word normalized="later">later </word>
    <word normalized="left">left </word>
    <word normalized="and">and </word>
    <word normalized="joined">joined </word>
    <word normalized="the">the </word>
    <word normalized="National">National </word>
    <word normalized="Wrestling">Wrestling </word>
    <word normalized="Alliance">Alliance </word>
    <word normalized="affiliate">affiliate </word>
    <word normalized="Jim">Jim </word>
    <word normalized="Crockett">Crockett </word>
    <word normalized="Promotions">Promotions </word>
    <word normalized="where">where </word>
    <word normalized="he">he </word>
    <word normalized="and">and </word>
    <word normalized="a">a </word>
    <word normalized="variety">variety </word>
    <word normalized="of">of </word>
    <word normalized="tag">tag </word>
    <word normalized="team">team </word>
    <word normalized="partners">partners </word>
    <word normalized="feuded">feuded </word>
    <word normalized="with">with </word>
    <word normalized="The">The </word>
    <word normalized="Road">Road </word>
    <word normalized="Warriors">Warriors</word>
    <word normalized="">. </word>
  </sentence>
  <sentence>
    <word normalized="He">He </word>
    <word normalized="returned">returned </word>
    <word normalized="to">to </word>
    <word normalized="Memphis">Memphis </word>
    <word normalized="Championship">Championship </word>
    <word normalized="Wrestling">Wrestling </word>
    <word normalized="in">in </word>
    <word normalized="nineteen">19 </word>
    <word normalized="hundred">hundred </word>
    <word normalized="eighty four">84</word>
    <word normalized="">, </word>
    <word normalized="this">this </word>
    <word normalized="time">time </word>
    <word normalized="as">as </word>
    <word normalized="">"</word>
    <word normalized="Ravishing">Ravishing</word>
    <word normalized="">" </word>
    <word normalized="Rick">Rick </word>
    <word normalized="Rude">Rude</word>
    <word normalized="">, </word>
    <word normalized="an">an </word>
    <word normalized="overconfident">overconfident</word>
    <word normalized="">, </word>
    <word normalized="arrogant">arrogant </word>
    <word normalized="heel">heel </word>
    <word normalized="managed">managed </word>
    <word normalized="by">by </word>
    <word normalized="Jimmy">Jimmy </word>
    <word normalized="Hart">Hart</word>
    <word normalized="">. </word>
  </sentence>
  <sentence>
    <word normalized="Rude">Rude </word>
    <word normalized="feuded">feuded </word>
    <word normalized="with">with </word>
    <word normalized="Jerry">Jerry </word>
    <word normalized="Lawler">Lawler </word>
    <word normalized="and">and </word>
    <word normalized="later">later </word>
    <word normalized="his">his </word>
    <word normalized="former">former </word>
    <word normalized="partner">partner</word>
    <word normalized="">, </word>
    <word normalized="King">King </word>
    <word normalized="Kong">Kong </word>
    <word normalized="Bundy">Bundy</word>
    <word normalized="">. </word>
  </sentence>
  <sentence>
    <word normalized="Rude">Rude </word>
    <word normalized="was">was </word>
    <word normalized="hired">hired </word>
    <word normalized="by">by </word>
    <word normalized="Championship">Championship </word>
    <word normalized="Wrestling">Wrestling </word>
    <word normalized="from">from </word>
    <word normalized="Florida">Florida </word>
    <word normalized="in">in </word>
    <word normalized="December">December </word>
    <word normalized="nineteen">19 </word>
    <word normalized="hundred">hundred </word>
    <word normalized="eighty four">84</word>
    <word normalized="">, </word>
    <word normalized="where">where </word>
    <word normalized="he">he </word>
    <word normalized="was">was </word>
    <word normalized="managed">managed </word>
    <word normalized="by">by </word>
    <word normalized="Percy">Percy </word>
    <word normalized="Pringle">Pringle </word>
    <word normalized="and">and </word>
    <word normalized="feuded">feuded </word>
    <word normalized="with">with </word>
    <word normalized="Billy">Billy </word>
    <word normalized="Jack">Jack </word>
    <word normalized="Haynes">Haynes </word>
    <word normalized="and">and </word>
    <word normalized="Wahoo">Wahoo </word>
    <word normalized="McDaniel">McDaniel</word>
    <word normalized="">, </word>
    <word normalized="while">while </word>
    <word normalized="teaming">teaming </word>
    <word normalized="with">with </word>
    <word normalized="Jesse">Jesse </word>
    <word normalized="Barr">Barr</word>
    <word normalized="">. </word>
  </sentence>
  <sentence>
    <word normalized="After">After </word>
    <word normalized="a">a </word>
    <word normalized="year">year</word>
    <word normalized="">, </word>
    <word normalized="he">he </word>
    <word normalized="jumped">jumped </word>
    <word normalized="to">to </word>
    <word normalized="World">World </word>
    <word normalized="Class">Class </word>
    <word normalized="Championship">Championship </word>
    <word normalized="Wrestling">Wrestling </word>
    <word normalized="">(</word>
    <word normalized="W C C W">WCCW</word>
    <word normalized="">) </word>
    <word normalized="along">along </word>
    <word normalized="with">with </word>
    <word normalized="Pringle">Pringle</word>
    <word normalized="">, </word>
    <word normalized="where">where </word>
    <word normalized="he">he </word>
    <word normalized="feuded">feuded </word>
    <word normalized="with">with </word>
    <word normalized="Kevin">Kevin </word>
    <word normalized="Von">Von </word>
    <word normalized="Erich">Erich </word>
    <word normalized="and">and </word>
    <word normalized="Chris">Chris </word>
    <word normalized="Adams">Adams</word>
    <word normalized="">. </word>
  </sentence>
  <sentence>
    <word normalized="After">After </word>
    <word normalized="losing">losing </word>
    <word normalized="the">the </word>
    <word normalized="W C C W">WCCW </word>
    <word normalized="Championship">Championship </word>
    <word normalized="to">to </word>
    <word normalized="Adams">Adams </word>
    <word normalized="in">in </word>
    <word normalized="July">July </word>
    <word normalized="19">19 </word>
    <word normalized="hundred">hundred </word>
    <word normalized="eighty six">86</word>
    <word normalized="">, </word>
    <word normalized="he">he </word>
    <word normalized="fired">fired </word>
    <word normalized="Pringle">Pringle </word>
    <word normalized="and">and </word>
    <word normalized="briefly">briefly </word>
    <word normalized="replaced">replaced </word>
    <word normalized="him">him </word>
    <word normalized="with">with </word>
    <word normalized="his">his </word>
    <word normalized="sister">sister</word>
    <word normalized="">, </word>
    <word normalized="Raven">Raven</word>
    <word normalized="">. </word>
  </sentence>
  <sentence>
    <word normalized="He">He </word>
    <word normalized="formed">formed </word>
    <word normalized="a">a </word>
    <word normalized="short lived">short-lived </word>
    <word normalized="tag">tag </word>
    <word normalized="team">team </word>
    <word normalized="with">with </word>
    <word normalized="The">The </word>
    <word normalized="Dingo">Dingo </word>
    <word normalized="Warrior">Warrior</word>
    <word normalized="">, </word>
    <word normalized="but">but </word>
    <word normalized="the">the </word>
    <word normalized="Warrior">Warrior </word>
    <word normalized="turned">turned </word>
    <word normalized="on">on </word>
    <word normalized="him">him </word>
    <word normalized="and">and </word>
    <word normalized="became">became </word>
    <word normalized="a">a </word>
    <word normalized="face">face</word>
    <word normalized="">. </word>
  </sentence>
  <sentence>
    <word normalized="In">In </word>
    <word normalized="September">September </word>
    <word normalized="nineteen">19 </word>
    <word normalized="hundred">hundred </word>
    <word normalized="eighty six">86</word>
    <word normalized="">, </word>
    <word normalized="Rude">Rude </word>
    <word normalized="returned">returned </word>
    <word normalized="to">to </word>
    <word normalized="Jim">Jim </word>
    <word normalized="Crockett">Crockett </word>
    <word normalized="Promotions">Promotions </word>
    <word normalized="and">and </word>
    <word normalized="joined">joined </word>
    <word normalized="Manny">Manny </word>
    <word normalized="Fernandez">Fernandez </word>
    <word normalized="and">and </word>
    <word normalized="his">his </word>
    <word normalized="manager">manager </word>
    <word normalized="Paul">Paul </word>
    <word normalized="Jones">Jones </word>
    <word normalized="in">in </word>
    <word normalized="their">their </word>
    <word normalized="rivalry">rivalry </word>
    <word normalized="with">with </word>
    <word normalized="Wahoo">Wahoo </word>
    <word normalized="McDaniel">McDaniel</word>
    <word normalized="">. </word>
  </sentence>
  <sentence>
    <word normalized="Rude">Rude </word>
    <word normalized="and">and </word>
    <word normalized="Fernandez">Fernandez</word>
    <word normalized="">, </word>
    <word normalized="known">known </word>
    <word normalized="collectively">collectively </word>
    <word normalized="as">as </word>
    <word normalized="the">the </word>
    <word normalized="">"</word>
    <word normalized="Awesome">Awesome </word>
    <word normalized="Twosome">Twosome</word>
    <word normalized="">"</word>
    <word normalized="">, </word>
    <word normalized="won">won </word>
    <word normalized="the">the </word>
    <word normalized="NWA">NWA </word>
    <word normalized="World">World </word>
    <word normalized="Tag">Tag </word>
    <word normalized="Team">Team </word>
    <word normalized="Championships">Championships </word>
    <word normalized="on">on </word>
    <word normalized="December">December </word>
    <word normalized="six">6 </word>
    <word normalized="nineteen">19 </word>
    <word normalized="hundred">hundred </word>
    <word normalized="eighty six">86 </word>
    <word normalized="from">from </word>
    <word normalized="The">The </word>
    <word normalized="Rock">Rock </word>
    <word normalized="">'</word>
    <word normalized="n">n</word>
    <word normalized="">' </word>
    <word normalized="Roll">Roll </word>
    <word normalized="Express">Express</word>
    <word normalized="">, </word>
    <word normalized="and">and </word>
    <word normalized="they">they </word>
    <word normalized="began">began </word>
    <word normalized="a">a </word>
    <word normalized="feud">feud </word>
    <word normalized="that">that </word>
    <word normalized="ended">ended </word>
    <word normalized="only">only </word>
    <word normalized="when">when </word>
    <word normalized="Rude">Rude </word>
    <word normalized="left">left </word>
    <word normalized="the">the </word>
    <word normalized="promotion">promotion </word>
    <word normalized="for">for </word>
    <word normalized="the">the </word>
    <word normalized="World">World </word>
    <word normalized="Wrestling">Wrestling </word>
    <word normalized="Federation">Federation </word>
    <word normalized="in">in </word>
    <word normalized="April">April </word>
    <word normalized="nineteen">19 </word>
    <word normalized="hundred">hundred </word>
    <word normalized="eighty seven">87</word>
    <word normalized="">. </word>
  </sentence>
  <sentence>
    <word normalized="To">To </word>
    <word normalized="explain">explain </word>
    <word normalized="the">the </word>
    <word normalized="sudden">sudden </word>
    <word normalized="departure">departure</word>
    <word normalized="">, </word>
    <word normalized="Jim">Jim </word>
    <word normalized="Crockett">Crockett</word>
    <word normalized="">, </word>
    <word normalized="Jr">Jr. </word>
    <word normalized="aired">aired </word>
    <word normalized="a">a </word>
    <word normalized="pre taped">pre-taped </word>
    <word normalized="non title">non-title </word>
    <word normalized="match">match </word>
    <word normalized="where">where </word>
    <word normalized="the">the </word>
    <word normalized="Express">Express </word>
    <word normalized="defeated">defeated </word>
    <word normalized="Rude">Rude </word>
    <word normalized="and">and </word>
    <word normalized="Fernandez">Fernandez </word>
    <word normalized="and">and </word>
    <word normalized="claimed">claimed </word>
    <word normalized="that">that </word>
    <word normalized="Rude">Rude </word>
    <word normalized="had">had </word>
    <word normalized="been">been </word>
    <word normalized="injured">injured </word>
    <word normalized="as">as </word>
    <word normalized="a">a </word>
    <word normalized="result">result</word>
    <word normalized="">. </word>
  </sentence>
  <sentence>
    <word normalized="Section">Section </word>
    <word normalized="one">1 </word>
    <word normalized="point">point </word>
    <word normalized="one">1 </word>
    <word normalized="World">World </word>
    <word normalized="Wrestling">Wrestling </word>
    <word normalized="Federation">Federation </word>
    <word normalized="">(</word>
    <word normalized="nineteen">19 </word>
    <word normalized="hundred">hundred </word>
    <word normalized="eighty seven to nineteen">87–19 </word>
    <word normalized="hundred">hundred </word>
    <word normalized="ninety">90</word>
    <word normalized="">) </word>
    <word normalized="In">In </word>
    <word normalized="the">the </word>
    <word normalized="W W F">WWF</word>
    <word normalized="">, </word>
    <word normalized="Rude">Rude </word>
    <word normalized="was">was </word>
    <word normalized="managed">managed </word>
    <word normalized="by">by </word>
    <word normalized="Bobby">Bobby </word>
    <word normalized="">"</word>
    <word normalized="The">The </word>
    <word normalized="Brain">Brain</word>
    <word normalized="">" </word>
    <word normalized="Heenan">Heenan </word>
    <word normalized="and">and </word>
    <word normalized="feuded">feuded </word>
    <word normalized="with">with </word>
    <word normalized="">"</word>
    <word normalized="mister">Mr. </word>
    <word normalized="Wonderful">Wonderful</word>
    <word normalized="">" </word>
    <word normalized="Paul">Paul </word>
    <word normalized="Orndorff">Orndorff </word>
    <word normalized="before">before </word>
    <word normalized="starting">starting </word>
    <word normalized="one">one </word>
    <word normalized="of">of </word>
    <word normalized="his">his </word>
    <word normalized="most">most </word>
    <word normalized="famous">famous </word>
    <word normalized="feuds">feuds </word>
    <word normalized="with">with </word>
    <word normalized="Jake">Jake </word>
    <word normalized="">"</word>
    <word normalized="The">The </word>
    <word normalized="Snake">Snake</word>
    <word normalized="">" </word>
    <word normalized="Roberts">Roberts</word>
    <word normalized="">. </word>
  </sentence>
  <sentence>
    <word normalized="Rude">Rude </word>
    <word normalized="had">had </word>
    <word normalized="a">a </word>
    <word normalized="routine">routine </word>
    <word normalized="where">where </word>
    <word normalized="before">before </word>
    <word normalized="the">the </word>
    <word normalized="match">match </word>
    <word normalized="he">he </word>
    <word normalized="would">would </word>
    <word normalized="make">make </word>
    <word normalized="a">a </word>
    <word normalized="show">show </word>
    <word normalized="of">of </word>
    <word normalized="removing">removing </word>
    <word normalized="his">his </word>
    <word normalized="robe">robe </word>
    <word normalized="while">while </word>
    <word normalized="insulting">insulting </word>
    <word normalized="the">the </word>
    <word normalized="males">males </word>
    <word normalized="in">in </word>
    <word normalized="the">the </word>
    <word normalized="crowd">crowd </word>
    <word normalized="and">and </word>
    <word normalized="after">after </word>
    <word normalized="his">his </word>
    <word normalized="victories">victories</word>
    <word normalized="">, </word>
    <word normalized="he">he </word>
    <word normalized="would">would </word>
    <word normalized="kiss">kiss </word>
    <word normalized="a">a </word>
    <word normalized="woman">woman </word>
    <word normalized="that">that </word>
    <word normalized="Heenan">Heenan </word>
    <word normalized="picked">picked </word>
    <word normalized="from">from </word>
    <word normalized="the">the </word>
    <word normalized="fans">fans</word>
    <word normalized="">. </word>
  </sentence>
  <sentence>
    <word normalized="In">In </word>
    <word normalized="one">one </word>
    <word normalized="storyline">storyline</word>
    <word normalized="">, </word>
    <word normalized="he">he </word>
    <word normalized="tried">tried </word>
    <word normalized="to">to </word>
    <word normalized="get">get </word>
    <word normalized="Roberts">Roberts</word>
    <word normalized="">' </word>
    <word normalized="real life">real-life </word>
    <word normalized="wife">wife</word>
    <word normalized="">, </word>
    <word normalized="Cheryl">Cheryl</word>
    <word normalized="">, </word>
    <word normalized="to">to </word>
    <word normalized="comply">comply</word>
    <word normalized="">, </word>
    <word normalized="aggravating">aggravating </word>
    <word normalized="Roberts">Roberts</word>
    <word normalized="">. </word>
  </sentence>
  <sentence>
    <word normalized="On">On </word>
    <word normalized="another">another </word>
    <word normalized="occasion">occasion </word>
    <word normalized="during">during </word>
    <word normalized="the">the </word>
    <word normalized="Roberts forward slash Rude">Roberts/Rude </word>
    <word normalized="feud">feud</word>
    <word normalized="">, </word>
    <word normalized="Rude">Rude </word>
    <word normalized="came">came </word>
    <word normalized="to">to </word>
    <word normalized="the">the </word>
    <word normalized="ring">ring </word>
    <word normalized="with">with </word>
    <word normalized="a">a </word>
    <word normalized="picture">picture </word>
    <word normalized="of">of </word>
    <word normalized="Cheryl">Cheryl </word>
    <word normalized="stenciled">stenciled </word>
    <word normalized="on">on </word>
    <word normalized="the">the </word>
    <word normalized="front">front </word>
    <word normalized="of">of </word>
    <word normalized="his">his </word>
    <word normalized="tights">tights</word>
    <word normalized="">. </word>
  </sentence>
  <sentence>
    <word normalized="A">A </word>
    <word normalized="furious">furious </word>
    <word normalized="Roberts">Roberts </word>
    <word normalized="charged">charged </word>
    <word normalized="the">the </word>
    <word normalized="ring">ring </word>
    <word normalized="and">and </word>
    <word normalized="stripped">stripped </word>
    <word normalized="Rude">Rude</word>
    <word normalized="">, </word>
    <word normalized="appearing">appearing </word>
    <word normalized="to">to </word>
    <word normalized="television">television </word>
    <word normalized="viewers">viewers </word>
    <word normalized="to">to </word>
    <word normalized="leave">leave </word>
    <word normalized="him">him </word>
    <word normalized="naked">naked</word>
    <word normalized="">, </word>
    <word normalized="although">although </word>
    <word normalized="the">the </word>
    <word normalized="live">live </word>
    <word normalized="audience">audience </word>
    <word normalized="saw">saw </word>
    <word normalized="him">him </word>
    <word normalized="stripped">stripped </word>
    <word normalized="to">to </word>
    <word normalized="a">a </word>
    <word normalized="thong">thong </word>
    <word normalized="instead">instead</word>
    <word normalized="">. </word>
  </sentence>
  <sentence>
    <word normalized="Rude s">Rude's </word>
    <word normalized="next">next </word>
    <word normalized="big">big </word>
    <word normalized="feud">feud </word>
    <word normalized="was">was </word>
    <word normalized="with">with </word>
    <word normalized="The">The </word>
    <word normalized="Ultimate">Ultimate </word>
    <word normalized="Warrior">Warrior </word>
    <word normalized="and">and </word>
    <word normalized="began">began </word>
    <word normalized="in">in </word>
    <word normalized="January">January </word>
    <word normalized="at">at </word>
    <word normalized="the">the </word>
    <word normalized="19">19 </word>
    <word normalized="hundred">hundred </word>
    <word normalized="eighty nine">89 </word>
    <word normalized="Royal">Royal </word>
    <word normalized="Rumble">Rumble </word>
    <word normalized="pay per view">pay-per-view </word>
    <word normalized="in">in </word>
    <word normalized="the">the </word>
    <word normalized="Super">Super </word>
    <word normalized="Posedown">Posedown </word>
    <word normalized="that">that </word>
    <word normalized="ended">ended </word>
    <word normalized="with">with </word>
    <word normalized="Rude">Rude </word>
    <word normalized="attacking">attacking </word>
    <word normalized="Warrior">Warrior </word>
    <word normalized="with">with </word>
    <word normalized="a">a </word>
    <word normalized="metal">metal </word>
    <word normalized="pose">pose </word>
    <word normalized="bar">bar</word>
    <word normalized="">. </word>
  </sentence>
  <sentence>
    <word normalized="With">With </word>
    <word normalized="help">help </word>
    <word normalized="from">from </word>
    <word normalized="Heenan">Heenan</word>
    <word normalized="">, </word>
    <word normalized="Rude">Rude </word>
    <word normalized="won">won </word>
    <word normalized="the">the </word>
    <word normalized="Intercontinental">Intercontinental </word>
    <word normalized="Championship">Championship </word>
    <word normalized="from">from </word>
    <word normalized="the">the </word>
    <word normalized="Warrior">Warrior </word>
    <word normalized="at">at </word>
    <word normalized="WrestleMania">WrestleMania </word>
    <word normalized="V">V</word>
    <word normalized="">, </word>
    <word normalized="before">before </word>
    <word normalized="dropping">dropping </word>
    <word normalized="it">it </word>
    <word normalized="back">back </word>
    <word normalized="to">to </word>
    <word normalized="the">the </word>
    <word normalized="Warrior">Warrior </word>
    <word normalized="at">at </word>
    <word normalized="SummerSlam">SummerSlam </word>
    <word normalized="nineteen">19 </word>
    <word normalized="hundred">hundred </word>
    <word normalized="eighty nine">89 </word>
    <word normalized="due">due </word>
    <word normalized="in">in </word>
    <word normalized="large">large </word>
    <word normalized="part">part </word>
    <word normalized="to">to </word>
    <word normalized="interference">interference </word>
    <word normalized="from">from </word>
    <word normalized="">"</word>
    <word normalized="Rowdy">Rowdy</word>
    <word normalized="">" </word>
    <word normalized="Roddy">Roddy </word>
    <word normalized="Piper">Piper</word>
    <word normalized="">. </word>
  </sentence>
  <sentence>
    <word normalized="Rude">Rude </word>
    <word normalized="then">then </word>
    <word normalized="feuded">feuded </word>
    <word normalized="with">with </word>
    <word normalized="Piper">Piper</word>
    <word normalized="">, </word>
    <word normalized="before">before </word>
    <word normalized="resuming">resuming </word>
    <word normalized="his">his </word>
    <word normalized="conflict">conflict </word>
    <word normalized="with">with </word>
    <word normalized="the">the </word>
    <word normalized="Warrior">Warrior </word>
    <word normalized="in">in </word>
    <word normalized="the">the </word>
    <word normalized="summer">summer </word>
    <word normalized="of">of </word>
    <word normalized="nineteen">19 </word>
    <word normalized="hundred">hundred </word>
    <word normalized="ninety">90 </word>
    <word normalized="after">after </word>
    <word normalized="the">the </word>
    <word normalized="Warrior">Warrior </word>
    <word normalized="had">had </word>
    <word normalized="won">won </word>
    <word normalized="the">the </word>
    <word normalized="W W F">WWF </word>
    <word normalized="Championship">Championship</word>
    <word normalized="">. </word>
  </sentence>
  <sentence>
    <word normalized="The">The </word>
    <word normalized="two">two </word>
    <word normalized="battled">battled </word>
    <word normalized="in">in </word>
    <word normalized="a">a </word>
    <word normalized="cage">cage </word>
    <word normalized="at">at </word>
    <word normalized="SummerSlam">SummerSlam </word>
    <word normalized="nineteen">19 </word>
    <word normalized="hundred">hundred </word>
    <word normalized="ninety">90</word>
    <word normalized="">. </word>
  </sentence>
  <sentence>
    <word normalized="Rude">Rude </word>
    <word normalized="failed">failed </word>
    <word normalized="to">to </word>
    <word normalized="win">win </word>
    <word normalized="the">the </word>
    <word normalized="title">title </word>
    <word normalized="and">and </word>
    <word normalized="departed">departed </word>
    <word normalized="from">from </word>
    <word normalized="W W F">WWF </word>
    <word normalized="in">in </word>
    <word normalized="October">October </word>
    <word normalized="nineteen">19 </word>
    <word normalized="hundred">hundred </word>
    <word normalized="ninety">90</word>
    <word normalized="">. </word>
  </sentence>
  <sentence>
    <word normalized="His">His </word>
    <word normalized="departure">departure </word>
    <word normalized="came">came </word>
    <word normalized="right">right </word>
    <word normalized="before">before </word>
    <word normalized="he">he </word>
    <word normalized="was">was </word>
    <word normalized="scheduled">scheduled </word>
    <word normalized="to">to </word>
    <word normalized="feud">feud </word>
    <word normalized="with">with </word>
    <word normalized="the">the </word>
    <word normalized="Big">Big </word>
    <word normalized="Boss">Boss </word>
    <word normalized="Man">Man</word>
    <word normalized="">, </word>
    <word normalized="which">which </word>
    <word normalized="had">had </word>
    <word normalized="its">its </word>
    <word normalized="potential">potential </word>
    <word normalized="start">start </word>
    <word normalized="when">when </word>
    <word normalized="Rude">Rude </word>
    <word normalized="started">started </word>
    <word normalized="to">to </word>
    <word normalized="make">make </word>
    <word normalized="degrading">degrading </word>
    <word normalized="comments">comments </word>
    <word normalized="about">about </word>
    <word normalized="The">The </word>
    <word normalized="Boss">Boss </word>
    <word normalized="Man s">Man's </word>
    <word normalized="mother">mother</word>
    <word normalized="">. </word>
  </sentence>
  <sentence>
    <word normalized="Section">Section </word>
    <word normalized="one">1 </word>
    <word normalized="point">point </word>
    <word normalized="two">2 </word>
    <word normalized="World">World </word>
    <word normalized="Championship">Championship </word>
    <word normalized="Wrestling">Wrestling </word>
    <word normalized="">(</word>
    <word normalized="nineteen">19 </word>
    <word normalized="hundred">hundred </word>
    <word normalized="ninety one to nineteen">91–19 </word>
    <word normalized="hundred">hundred </word>
    <word normalized="ninety four">94</word>
    <word normalized="">) </word>
    <word normalized="Rude">Rude </word>
    <word normalized="returned">returned </word>
    <word normalized="to">to </word>
    <word normalized="Jim">Jim </word>
    <word normalized="Crockett">Crockett </word>
    <word normalized="Promotions">Promotions</word>
    <word normalized="">, </word>
    <word normalized="eventually">eventually </word>
    <word normalized="known">known </word>
    <word normalized="as">as </word>
    <word normalized="World">World </word>
    <word normalized="Championship">Championship </word>
    <word normalized="Wrestling">Wrestling </word>
    <word normalized="">(</word>
    <word normalized="W C W">WCW</word>
    <word normalized="">)</word>
    <word normalized="">, </word>
    <word normalized="as">as </word>
    <word normalized="The">The </word>
    <word normalized="Halloween">Halloween </word>
    <word normalized="Phantom">Phantom </word>
    <word normalized="at">at </word>
    <word normalized="Halloween">Halloween </word>
    <word normalized="Havoc">Havoc </word>
    <word normalized="on">on </word>
    <word normalized="October">October </word>
    <word normalized="27">27 </word>
    <word normalized="nineteen">19 </word>
    <word normalized="hundred">hundred </word>
    <word normalized="ninety one">91</word>
    <word normalized="">, </word>
    <word normalized="unmasking">unmasking </word>
    <word normalized="himself">himself </word>
    <word normalized="later">later </word>
    <word normalized="that">that </word>
    <word normalized="night">night</word>
    <word normalized="">. </word>
  </sentence>
  <sentence>
    <word normalized="He">He </word>
    <word normalized="founded">founded </word>
    <word normalized="and">and </word>
    <word normalized="led">led </word>
    <word normalized="The">The </word>
    <word normalized="Dangerous">Dangerous </word>
    <word normalized="Alliance">Alliance</word>
    <word normalized="">, </word>
    <word normalized="consisting">consisting </word>
    <word normalized="of">of </word>
    <word normalized="himself">himself</word>
    <word normalized="">, </word>
    <word normalized="Paul">Paul </word>
    <word normalized="E">E. </word>
    <word normalized="Dangerously">Dangerously</word>
    <word normalized="">, </word>
    <word normalized="Madusa">Madusa</word>
    <word normalized="">, </word>
    <word normalized="Arn">Arn </word>
    <word normalized="Anderson">Anderson</word>
    <word normalized="">, </word>
    <word normalized="Bobby">Bobby </word>
    <word normalized="Eaton">Eaton</word>
    <word normalized="">, </word>
    <word normalized="Larry">Larry </word>
    <word normalized="Zbyszko">Zbyszko</word>
    <word normalized="">, </word>
    <word normalized="and">and </word>
    <word normalized="">"</word>
    <word normalized="Stunning">Stunning</word>
    <word normalized="">" </word>
    <word normalized="Steve">Steve </word>
    <word normalized="Austin">Austin</word>
    <word normalized="">. </word>
  </sentence>
  <sentence>
    <word normalized="Rude">Rude </word>
    <word normalized="won">won </word>
    <word normalized="the">the </word>
    <word normalized="United">United </word>
    <word normalized="States">States </word>
    <word normalized="Championship">Championship </word>
    <word normalized="from">from </word>
    <word normalized="Sting">Sting </word>
    <word normalized="and">and </word>
    <word normalized="feuded">feuded </word>
    <word normalized="with">with </word>
    <word normalized="Ricky">Ricky </word>
    <word normalized="Steamboat">Steamboat</word>
    <word normalized="">, </word>
    <word normalized="at">at </word>
    <word normalized="one">one </word>
    <word normalized="point">point </word>
    <word normalized="giving">giving </word>
    <word normalized="Steamboat">Steamboat </word>
    <word normalized="a">a </word>
    <word normalized="kayfabe">kayfabe </word>
    <word normalized="broken">broken </word>
    <word normalized="nose">nose </word>
    <word normalized="in">in </word>
    <word normalized="a">a </word>
    <word normalized="gang">gang </word>
    <word normalized="attack">attack</word>
    <word normalized="">. </word>
  </sentence>
  <sentence>
    <word normalized="In">In </word>
    <word normalized="nineteen">19 </word>
    <word normalized="hundred">hundred </word>
    <word normalized="ninety two">92</word>
    <word normalized="">, </word>
    <word normalized="Rude">Rude </word>
    <word normalized="and">and </word>
    <word normalized="Madusa">Madusa </word>
    <word normalized="left">left </word>
    <word normalized="The">The </word>
    <word normalized="Dangerous">Dangerous </word>
    <word normalized="Alliance">Alliance </word>
    <word normalized="and">and </word>
    <word normalized="feuded">feuded </word>
    <word normalized="with">with </word>
    <word normalized="Nikita">Nikita </word>
    <word normalized="Koloff">Koloff</word>
    <word normalized="">. </word>
  </sentence>
  <sentence>
    <word normalized="Rude">Rude </word>
    <word normalized="challenged">challenged </word>
    <word normalized="reigning">reigning </word>
    <word normalized="World">World </word>
    <word normalized="Heavyweight">Heavyweight </word>
    <word normalized="Champion">Champion </word>
    <word normalized="Ron">Ron </word>
    <word normalized="Simmons">Simmons </word>
    <word normalized="on">on </word>
    <word normalized="several">several </word>
    <word normalized="occasions">occasions </word>
    <word normalized="but">but </word>
    <word normalized="did">did </word>
    <word normalized="not">not </word>
    <word normalized="defeat">defeat </word>
    <word normalized="him">him</word>
    <word normalized="">. </word>
  </sentence>
  <sentence>
    <word normalized="He">He </word>
    <word normalized="was">was </word>
    <word normalized="injured">injured </word>
    <word normalized="in">in </word>
    <word normalized="December">December </word>
    <word normalized="of">of </word>
    <word normalized="that">that </word>
    <word normalized="year">year </word>
    <word normalized="and">and </word>
    <word normalized="was">was </word>
    <word normalized="forced">forced </word>
    <word normalized="to">to </word>
    <word normalized="forfeit">forfeit </word>
    <word normalized="the">the </word>
    <word normalized="United">United </word>
    <word normalized="States">States </word>
    <word normalized="Championship">Championship</word>
    <word normalized="">. </word>
  </sentence>
  <sentence>
    <word normalized="Rude">Rude </word>
    <word normalized="returned">returned </word>
    <word normalized="alone">alone </word>
    <word normalized="in">in </word>
    <word normalized="April">April </word>
    <word normalized="nineteen">19 </word>
    <word normalized="hundred">hundred </word>
    <word normalized="ninety three">93 </word>
    <word normalized="and">and </word>
    <word normalized="tried">tried </word>
    <word normalized="to">to </word>
    <word normalized="reclaim">reclaim </word>
    <word normalized="the">the </word>
    <word normalized="title">title </word>
    <word normalized="from">from </word>
    <word normalized="Dustin">Dustin </word>
    <word normalized="Rhodes">Rhodes</word>
    <word normalized="">, </word>
    <word normalized="who">who </word>
    <word normalized="had">had </word>
    <word normalized="won">won </word>
    <word normalized="it">it </word>
    <word normalized="while">while </word>
    <word normalized="he">he </word>
    <word normalized="was">was </word>
    <word normalized="injured">injured</word>
    <word normalized="">. </word>
  </sentence>
  <sentence>
    <word normalized="The">The </word>
    <word normalized="title">title </word>
    <word normalized="was">was </word>
    <word normalized="eventually">eventually </word>
    <word normalized="held">held </word>
    <word normalized="up">up </word>
    <word normalized="after">after </word>
    <word normalized="several">several </word>
    <word normalized="controversial">controversial </word>
    <word normalized="finishes">finishes </word>
    <word normalized="to">to </word>
    <word normalized="matches">matches </word>
    <word normalized="between">between </word>
    <word normalized="the">the </word>
    <word normalized="two">two</word>
    <word normalized="">, </word>
    <word normalized="although">although </word>
    <word normalized="Rhodes">Rhodes </word>
    <word normalized="regained">regained </word>
    <word normalized="the">the </word>
    <word normalized="title">title </word>
    <word normalized="in">in </word>
    <word normalized="a">a </word>
    <word normalized="rematch">rematch</word>
    <word normalized="">. </word>
  </sentence>
  <sentence>
    <word normalized="Rude">Rude </word>
    <word normalized="switched">switched </word>
    <word normalized="his">his </word>
    <word normalized="sights">sights </word>
    <word normalized="to">to </word>
    <word normalized="the">the </word>
    <word normalized="NWA">NWA </word>
    <word normalized="World">World </word>
    <word normalized="Heavyweight">Heavyweight </word>
    <word normalized="Championship">Championship</word>
    <word normalized="">, </word>
    <word normalized="making">making </word>
    <word normalized="his">his </word>
    <word normalized="intentions">intentions </word>
    <word normalized="clear">clear </word>
    <word normalized="on">on </word>
    <word normalized="August">August </word>
    <word normalized="twenty eight">28 </word>
    <word normalized="nineteen">19 </word>
    <word normalized="hundred">hundred </word>
    <word normalized="ninety three">93</word>
    <word normalized="">, </word>
    <word normalized="when">when </word>
    <word normalized="he">he </word>
    <word normalized="was">was </word>
    <word normalized="the">the </word>
    <word normalized="guest">guest </word>
    <word normalized="on">on </word>
    <word normalized="then champion">then-champion </word>
    <word normalized="Ric">Ric </word>
    <word normalized="Flair s">Flair's </word>
    <word normalized="">"</word>
    <word normalized="A">A </word>
    <word normalized="Flair">Flair </word>
    <word normalized="For">For </word>
    <word normalized="the">the </word>
    <word normalized="Gold">Gold</word>
    <word normalized="">" </word>
    <word normalized="talk">talk </word>
    <word normalized="segment">segment</word>
    <word normalized="">. </word>
  </sentence>
  <sentence>
    <word normalized="Rude">Rude </word>
    <word normalized="defeated">defeated </word>
    <word normalized="Flair">Flair </word>
    <word normalized="for">for </word>
    <word normalized="the">the </word>
    <word normalized="title">title </word>
    <word normalized="in">in </word>
    <word normalized="September">September </word>
    <word normalized="nineteen">19 </word>
    <word normalized="hundred">hundred </word>
    <word normalized="ninety three">93 </word>
    <word normalized="at">at </word>
    <word normalized="Fall">Fall </word>
    <word normalized="Brawl">Brawl</word>
    <word normalized="">. </word>
  </sentence>
  <sentence>
    <word normalized="As">As </word>
    <word normalized="W C W">WCW </word>
    <word normalized="had">had </word>
    <word normalized="recently">recently </word>
    <word normalized="withdrawn">withdrawn </word>
    <word normalized="from">from </word>
    <word normalized="the">the </word>
    <word normalized="NWA">NWA</word>
    <word normalized="">, </word>
    <word normalized="the">the </word>
    <word normalized="title">title </word>
    <word normalized="could">could </word>
    <word normalized="no">no </word>
    <word normalized="longer">longer </word>
    <word normalized="be">be </word>
    <word normalized="called">called </word>
    <word normalized="the">the </word>
    <word normalized="NWA">NWA </word>
    <word normalized="World">World </word>
    <word normalized="Heavyweight">Heavyweight </word>
    <word normalized="Championship">Championship </word>
    <word normalized="">(</word>
    <word normalized="W C W">WCW </word>
    <word normalized="had">had </word>
    <word normalized="purchased">purchased </word>
    <word normalized="the">the </word>
    <word normalized="belt">belt </word>
    <word normalized="itself">itself</word>
    <word normalized="">, </word>
    <word normalized="however">however</word>
    <word normalized="">)</word>
    <word normalized="">. </word>
  </sentence>
  <sentence>
    <word normalized="The">The </word>
    <word normalized="title">title </word>
    <word normalized="was">was </word>
    <word normalized="renamed">renamed </word>
    <word normalized="the">the </word>
    <word normalized="W C W">WCW </word>
    <word normalized="International">International </word>
    <word normalized="World">World </word>
    <word normalized="Heavyweight">Heavyweight </word>
    <word normalized="Championship">Championship</word>
    <word normalized="">, </word>
    <word normalized="which">which </word>
    <word normalized="Rude">Rude </word>
    <word normalized="lost">lost </word>
    <word normalized="to">to </word>
    <word normalized="Hiroshi">Hiroshi </word>
    <word normalized="Hase">Hase </word>
    <word normalized="on">on </word>
    <word normalized="March">March </word>
    <word normalized="16">16 </word>
    <word normalized="nineteen">19 </word>
    <word normalized="hundred">hundred </word>
    <word normalized="ninety four">94 </word>
    <word normalized="in">in </word>
    <word normalized="Tokyo">Tokyo</word>
    <word normalized="">, </word>
    <word normalized="Japan">Japan</word>
    <word normalized="">. </word>
  </sentence>
  <sentence>
    <word normalized="Rude">Rude </word>
    <word normalized="regained">regained </word>
    <word normalized="the">the </word>
    <word normalized="title">title </word>
    <word normalized="just">just </word>
    <word normalized="eight">eight </word>
    <word normalized="days">days </word>
    <word normalized="later">later </word>
    <word normalized="in">in </word>
    <word normalized="Kyoto">Kyoto</word>
    <word normalized="">, </word>
    <word normalized="Japan">Japan</word>
    <word normalized="">. </word>
  </sentence>
  <sentence>
    <word normalized="After">After </word>
    <word normalized="dropping">dropping </word>
    <word normalized="the">the </word>
    <word normalized="title">title </word>
    <word normalized="to">to </word>
    <word normalized="Sting">Sting </word>
    <word normalized="on">on </word>
    <word normalized="April">April </word>
    <word normalized="seventeen">17</word>
    <word normalized="">, </word>
    <word normalized="Rude">Rude </word>
    <word normalized="pinned">pinned </word>
    <word normalized="Sting">Sting </word>
    <word normalized="on">on </word>
    <word normalized="May">May </word>
    <word normalized="one">1 </word>
    <word normalized="in">in </word>
    <word normalized="Fukuoka">Fukuoka </word>
    <word normalized="to">to </word>
    <word normalized="become">become </word>
    <word normalized="a">a </word>
    <word normalized="three">three </word>
    <word normalized="time">time </word>
    <word normalized="champion">champion</word>
    <word normalized="">. </word>
  </sentence>
  <sentence>
    <word normalized="Rude">Rude</word>
    <word normalized="">, </word>
    <word normalized="however">however</word>
    <word normalized="">, </word>
    <word normalized="injured">injured </word>
    <word normalized="his">his </word>
    <word normalized="neck">neck </word>
    <word normalized="during">during </word>
    <word normalized="the">the </word>
    <word normalized="match">match</word>
    <word normalized="">; </word>
    <word normalized="unable">unable </word>
    <word normalized="to">to </word>
    <word normalized="wrestle">wrestle</word>
    <word normalized="">, </word>
    <word normalized="he">he </word>
    <word normalized="was">was </word>
    <word normalized="stripped">stripped </word>
    <word normalized="of">of </word>
    <word normalized="the">the </word>
    <word normalized="title">title </word>
    <word normalized="">(</word>
    <word normalized="with">with </word>
    <word normalized="the">the </word>
    <word normalized="storyline">storyline </word>
    <word normalized="excuse">excuse </word>
    <word normalized="that">that </word>
    <word normalized="he">he </word>
    <word normalized="was">was </word>
    <word normalized="found">found </word>
    <word normalized="to">to </word>
    <word normalized="have">have </word>
    <word normalized="used">used </word>
    <word normalized="the">the </word>
    <word normalized="title">title </word>
    <word normalized="belt">belt </word>
    <word normalized="as">as </word>
    <word normalized="a">a </word>
    <word normalized="weapon">weapon </word>
    <word normalized="in">in </word>
    <word normalized="the">the </word>
    <word normalized="course">course </word>
    <word normalized="of">of </word>
    <word normalized="the">the </word>
    <word normalized="match">match</word>
    <word normalized="">)</word>
    <word normalized="">. </word>
  </sentence>
  <sentence>
    <word normalized="Rude">Rude </word>
    <word normalized="retired">retired </word>
    <word normalized="shortly">shortly </word>
    <word normalized="thereafter">thereafter</word>
    <word normalized="">. </word>
  </sentence>
  <sentence>
    <word normalized="Section">Section </word>
    <word normalized="1">1 </word>
    <word normalized="point">point </word>
    <word normalized="three">3 </word>
    <word normalized="Extreme">Extreme </word>
    <word normalized="Championship">Championship </word>
    <word normalized="Wrestling">Wrestling </word>
    <word normalized="and">and </word>
    <word normalized="W W F">WWF </word>
    <word normalized="return">return </word>
    <word normalized="">(</word>
    <word normalized="nineteen">19 </word>
    <word normalized="hundred">hundred </word>
    <word normalized="ninety seven">97</word>
    <word normalized="">) </word>
    <word normalized="Rude">Rude </word>
    <word normalized="collected">collected </word>
    <word normalized="on">on </word>
    <word normalized="an">an </word>
    <word normalized="insurance">insurance </word>
    <word normalized="policy">policy </word>
    <word normalized="and">and </word>
    <word normalized="did">did </word>
    <word normalized="not">not </word>
    <word normalized="compete">compete </word>
    <word normalized="in">in </word>
    <word normalized="wrestling">wrestling </word>
    <word normalized="again">again </word>
    <word normalized="until">until </word>
    <word normalized="19">19 </word>
    <word normalized="hundred">hundred </word>
    <word normalized="ninety seven">97</word>
    <word normalized="">, </word>
    <word normalized="when">when </word>
    <word normalized="he">he </word>
    <word normalized="joined">joined </word>
    <word normalized="Extreme">Extreme </word>
    <word normalized="Championship">Championship </word>
    <word normalized="Wrestling">Wrestling </word>
    <word normalized="">(</word>
    <word normalized="ECW">ECW</word>
    <word normalized="">) </word>
    <word normalized="as">as </word>
    <word normalized="a">a </word>
    <word normalized="masked">masked </word>
    <word normalized="man">man </word>
    <word normalized="who">who </word>
    <word normalized="harassed">harassed </word>
    <word normalized="Shane">Shane </word>
    <word normalized="Douglas">Douglas</word>
    <word normalized="">, </word>
    <word normalized="at">at </word>
    <word normalized="one">one </word>
    <word normalized="point">point </word>
    <word normalized="spanking">spanking </word>
    <word normalized="Francine">Francine</word>
    <word normalized="">. </word>
  </sentence>
  <sentence>
    <word normalized="He">He </word>
    <word normalized="eventually">eventually </word>
    <word normalized="unmasked">unmasked </word>
    <word normalized="and">and </word>
    <word normalized="became">became </word>
    <word normalized="a">a </word>
    <word normalized="color">color </word>
    <word normalized="commentator">commentator</word>
    <word normalized="">. </word>
  </sentence>
  <sentence>
    <word normalized="He">He </word>
    <word normalized="later">later </word>
    <word normalized="aligned">aligned </word>
    <word normalized="himself">himself</word>
    <word normalized="">, </word>
    <word normalized="for">for </word>
    <word normalized="a">a </word>
    <word normalized="short">short </word>
    <word normalized="time">time</word>
    <word normalized="">, </word>
    <word normalized="with">with </word>
    <word normalized="Shane">Shane </word>
    <word normalized="Douglas">Douglas </word>
    <word normalized="and">and </word>
    <word normalized="his">his </word>
    <word normalized="Triple">Triple </word>
    <word normalized="Threat">Threat </word>
    <word normalized="stable">stable</word>
    <word normalized="">. </word>
  </sentence>
  <sentence>
    <word normalized="During">During </word>
    <word normalized="the">the </word>
    <word normalized="ECW">ECW </word>
    <word normalized="versus">versus </word>
    <word normalized="USWA">USWA </word>
    <word normalized="forward slash">/ </word>
    <word normalized="W W F">WWF </word>
    <word normalized="inter company">inter-company </word>
    <word normalized="competition">competition</word>
    <word normalized="">, </word>
    <word normalized="Rude">Rude </word>
    <word normalized="helped">helped </word>
    <word normalized="Jerry">Jerry </word>
    <word normalized="">"</word>
    <word normalized="The">The </word>
    <word normalized="King">King</word>
    <word normalized="">" </word>
    <word normalized="Lawler">Lawler </word>
    <word normalized="defeat">defeat </word>
    <word normalized="ECW">ECW </word>
    <word normalized="mainstays">mainstays </word>
    <word normalized="Tommy">Tommy </word>
    <word normalized="Dreamer">Dreamer </word>
    <word normalized="and">and </word>
    <word normalized="The">The </word>
    <word normalized="Sandman">Sandman</word>
    <word normalized="">. </word>
  </sentence>
  <sentence>
    <word normalized="Rude">Rude </word>
    <word normalized="later">later </word>
    <word normalized="returned">returned </word>
    <word normalized="to">to </word>
    <word normalized="W W F">WWF </word>
    <word normalized="as">as </word>
    <word normalized="an">an </word>
    <word normalized="">"</word>
    <word normalized="insurance">insurance </word>
    <word normalized="policy">policy</word>
    <word normalized="">" </word>
    <word normalized="of">of </word>
    <word normalized="the">the </word>
    <word normalized="D Generation">D-Generation </word>
    <word normalized="X">X </word>
    <word normalized="stable">stable </word>
    <word normalized="">(</word>
    <word normalized="Shawn">Shawn </word>
    <word normalized="Michaels">Michaels</word>
    <word normalized="">, </word>
    <word normalized="Triple">Triple </word>
    <word normalized="H">H</word>
    <word normalized="">, </word>
    <word normalized="and">and </word>
    <word normalized="Chyna">Chyna</word>
    <word normalized="">)</word>
    <word normalized="">. </word>
  </sentence>
  <sentence>
    <word normalized="He">He </word>
    <word normalized="assisted">assisted </word>
    <word normalized="with">with </word>
    <word normalized="several">several </word>
    <word normalized="sneak">sneak </word>
    <word normalized="attacks">attacks </word>
    <word normalized="on">on </word>
    <word normalized="The">The </word>
    <word normalized="Undertaker">Undertaker</word>
    <word normalized="">. </word>
  </sentence>
  <sentence>
    <word normalized="He">He </word>
    <word normalized="left">left </word>
    <word normalized="W W F">WWF </word>
    <word normalized="after">after </word>
    <word normalized="the">the </word>
    <word normalized="Montreal">Montreal </word>
    <word normalized="Screwjob">Screwjob </word>
    <word normalized="at">at </word>
    <word normalized="Survivor">Survivor </word>
    <word normalized="Series">Series </word>
    <word normalized="19">19 </word>
    <word normalized="hundred">hundred </word>
    <word normalized="ninety seven">97</word>
    <word normalized="">. </word>
  </sentence>
  <sentence>
    <word normalized="According">According </word>
    <word normalized="to">to </word>
    <word normalized="Bret">Bret </word>
    <word normalized="Hart">Hart</word>
    <word normalized="">, </word>
    <word normalized="Rude">Rude </word>
    <word normalized="stayed">stayed </word>
    <word normalized="in">in </word>
    <word normalized="the">the </word>
    <word normalized="locker">locker </word>
    <word normalized="room">room </word>
    <word normalized="during">during </word>
    <word normalized="Bret s">Bret's </word>
    <word normalized="confrontation">confrontation </word>
    <word normalized="with">with </word>
    <word normalized="Vince">Vince </word>
    <word normalized="McMahon">McMahon</word>
    <word normalized="">. </word>
  </sentence>
  <sentence>
    <word normalized="Rude">Rude </word>
    <word normalized="then">then </word>
    <word normalized="called">called </word>
    <word normalized="Eric">Eric </word>
    <word normalized="Bischoff">Bischoff </word>
    <word normalized="and">and </word>
    <word normalized="informed">informed </word>
    <word normalized="him">him </word>
    <word normalized="what">what </word>
    <word normalized="had">had </word>
    <word normalized="happened">happened </word>
    <word normalized="was">was </word>
    <word normalized="in">in </word>
    <word normalized="fact">fact </word>
    <word normalized="real">real</word>
    <word normalized="">. </word>
  </sentence>
  <sentence>
    <word normalized="As">As </word>
    <word normalized="Rude">Rude </word>
    <word normalized="was">was </word>
    <word normalized="not">not </word>
    <word normalized="signed">signed </word>
    <word normalized="to">to </word>
    <word normalized="a">a </word>
    <word normalized="full time">full-time </word>
    <word normalized="contract">contract </word>
    <word normalized="with">with </word>
    <word normalized="W W F">WWF</word>
    <word normalized="">, </word>
    <word normalized="and">and </word>
    <word normalized="was">was </word>
    <word normalized="performing">performing </word>
    <word normalized="on">on </word>
    <word normalized="_a">a </word>
    <word normalized="">"</word>
    <word normalized="pay per appearance">pay-per-appearance</word>
    <word normalized="">" </word>
    <word normalized="basis">basis</word>
    <word normalized="">, </word>
    <word normalized="Rude">Rude </word>
    <word normalized="was">was </word>
    <word normalized="able">able </word>
    <word normalized="to">to </word>
    <word normalized="negotiate">negotiate </word>
    <word normalized="a">a </word>
    <word normalized="deal">deal </word>
    <word normalized="with">with </word>
    <word normalized="Bischoff">Bischoff </word>
    <word normalized="and">and </word>
    <word normalized="W C W">WCW</word>
    <word normalized="">, </word>
    <word normalized="in">in </word>
    <word normalized="part">part </word>
    <word normalized="due">due </word>
    <word normalized="to">to </word>
    <word normalized="his">his </word>
    <word normalized="anger">anger </word>
    <word normalized="over">over </word>
    <word normalized="the">the </word>
    <word normalized="Montreal">Montreal </word>
    <word normalized="Screwjob">Screwjob</word>
    <word normalized="">. </word>
  </sentence>
  <sentence>
    <word normalized="Section">Section </word>
    <word normalized="one">1 </word>
    <word normalized="point">point </word>
    <word normalized="four">4 </word>
    <word normalized="Return">Return </word>
    <word normalized="to">to </word>
    <word normalized="W C W">WCW </word>
    <word normalized="">(</word>
    <word normalized="nineteen">19 </word>
    <word normalized="hundred">hundred </word>
    <word normalized="ninety seven to nineteen">97–19 </word>
    <word normalized="hundred">hundred </word>
    <word normalized="ninety eight">98</word>
    <word normalized="">) </word>
    <word normalized="Rude">Rude </word>
    <word normalized="appeared">appeared </word>
    <word normalized="on">on </word>
    <word normalized="both">both </word>
    <word normalized="W W F">WWF </word>
    <word normalized="Raw">Raw </word>
    <word normalized="is">is </word>
    <word normalized="War">War </word>
    <word normalized="and">and </word>
    <word normalized="W C W">WCW </word>
    <word normalized="Monday">Monday </word>
    <word normalized="Nitro">Nitro </word>
    <word normalized="on">on </word>
    <word normalized="November">November </word>
    <word normalized="17">17 </word>
    <word normalized="nineteen">19 </word>
    <word normalized="hundred">hundred </word>
    <word normalized="ninety seven">97</word>
    <word normalized="">. </word>
  </sentence>
  <sentence>
    <word normalized="A">A </word>
    <word normalized="more">more </word>
    <word normalized="clean shaven">clean-shaven </word>
    <word normalized="Rude">Rude </word>
    <word normalized="appeared">appeared </word>
    <word normalized="on">on </word>
    <word normalized="Nitro">Nitro</word>
    <word normalized="">, </word>
    <word normalized="which">which </word>
    <word normalized="was">was </word>
    <word normalized="live">live</word>
    <word normalized="">, </word>
    <word normalized="and">and </word>
    <word normalized="proceeded">proceeded </word>
    <word normalized="to">to </word>
    <word normalized="criticize">criticize </word>
    <word normalized="W W F">WWF</word>
    <word normalized="">, </word>
    <word normalized="calling">calling </word>
    <word normalized="the">the </word>
    <word normalized="company">company </word>
    <word normalized="the">the </word>
    <word normalized="">"</word>
    <word normalized="Titanic">Titanic</word>
    <word normalized="">" </word>
    <word normalized="">(</word>
    <word normalized="a">a </word>
    <word normalized="reference">reference </word>
    <word normalized="to">to </word>
    <word normalized="Titan">Titan </word>
    <word normalized="Enterprises">Enterprises</word>
    <word normalized="">, </word>
    <word normalized="as">as </word>
    <word normalized="WWF s">WWF's </word>
    <word normalized="parent">parent </word>
    <word normalized="company">company </word>
    <word normalized="was">was </word>
    <word normalized="then">then </word>
    <word normalized="known">known</word>
    <word normalized="">, </word>
    <word normalized="as">as </word>
    <word normalized="the">the </word>
    <word normalized="">"</word>
    <word normalized="sinking">sinking </word>
    <word normalized="ship">ship</word>
    <word normalized="">"</word>
    <word normalized="">)</word>
    <word normalized="">. </word>
  </sentence>
  <sentence>
    <word normalized="An">An </word>
    <word normalized="hour">hour </word>
    <word normalized="later">later </word>
    <word normalized="on">on </word>
    <word normalized="RAW">RAW </word>
    <word normalized="">(</word>
    <word normalized="which">which </word>
    <word normalized="had">had </word>
    <word normalized="been">been </word>
    <word normalized="taped">taped </word>
    <word normalized="six">six </word>
    <word normalized="days">days </word>
    <word normalized="earlier">earlier</word>
    <word normalized="">)</word>
    <word normalized="">, </word>
    <word normalized="Rude">Rude </word>
    <word normalized="then">then </word>
    <word normalized="appeared">appeared </word>
    <word normalized="with">with </word>
    <word normalized="a">a </word>
    <word normalized="beard">beard</word>
    <word normalized="">. </word>
  </sentence>
  <sentence>
    <word normalized="Rude">Rude </word>
    <word normalized="also">also </word>
    <word normalized="appeared">appeared </word>
    <word normalized="on">on </word>
    <word normalized="ECW s">ECW's </word>
    <word normalized="Hardcore">Hardcore </word>
    <word normalized="T V">TV </word>
    <word normalized="during">during </word>
    <word normalized="that">that </word>
    <word normalized="weekend">weekend </word>
    <word normalized="">(</word>
    <word normalized="November">November </word>
    <word normalized="fourteen to sixteen">14–16 </word>
    <word normalized="as">as </word>
    <word normalized="the">the </word>
    <word normalized="show">show </word>
    <word normalized="was">was </word>
    <word normalized="syndicated">syndicated </word>
    <word normalized="differently">differently </word>
    <word normalized="depending">depending </word>
    <word normalized="on">on </word>
    <word normalized="the">the </word>
    <word normalized="market">market</word>
    <word normalized="">)</word>
    <word normalized="">. </word>
  </sentence>
  <sentence>
    <word normalized="Rude">Rude </word>
    <word normalized="was">was </word>
    <word normalized="still">still </word>
    <word normalized="making">making </word>
    <word normalized="ECW">ECW </word>
    <word normalized="appearances">appearances </word>
    <word normalized="while">while </word>
    <word normalized="in">in </word>
    <word normalized="D Generation">D-Generation </word>
    <word normalized="X">X. </word>
    <word normalized="In">In </word>
    <word normalized="W C W">WCW</word>
    <word normalized="">, </word>
    <word normalized="Rude">Rude </word>
    <word normalized="became">became </word>
    <word normalized="a">a </word>
    <word normalized="member">member </word>
    <word normalized="of">of </word>
    <word normalized="the">the </word>
    <word normalized="nWo">nWo</word>
    <word normalized="">, </word>
    <word normalized="managing">managing </word>
    <word normalized="his">his </word>
    <word normalized="friend">friend </word>
    <word normalized="Curt">Curt </word>
    <word normalized="Hennig">Hennig</word>
    <word normalized="">. </word>
  </sentence>
  <sentence>
    <word normalized="When">When </word>
    <word normalized="the">the </word>
    <word normalized="nWo">nWo </word>
    <word normalized="split">split</word>
    <word normalized="">, </word>
    <word normalized="Hennig">Hennig </word>
    <word normalized="and">and </word>
    <word normalized="Rude">Rude </word>
    <word normalized="joined">joined </word>
    <word normalized="the">the </word>
    <word normalized="nWo">nWo </word>
    <word normalized="Wolfpac">Wolfpac</word>
    <word normalized="">, </word>
    <word normalized="and">and </word>
    <word normalized="they">they </word>
    <word normalized="tried">tried </word>
    <word normalized="to">to </word>
    <word normalized="motivate">motivate </word>
    <word normalized="Konnan">Konnan </word>
    <word normalized="to">to </word>
    <word normalized="defeat">defeat </word>
    <word normalized="Goldberg">Goldberg</word>
    <word normalized="">, </word>
    <word normalized="who">who </word>
    <word normalized="was">was </word>
    <word normalized="undefeated">undefeated </word>
    <word normalized="at">at </word>
    <word normalized="the">the </word>
    <word normalized="time">time</word>
    <word normalized="">. </word>
  </sentence>
  <sentence>
    <word normalized="When">When </word>
    <word normalized="Konnan">Konnan </word>
    <word normalized="was">was </word>
    <word normalized="defeated">defeated </word>
    <word normalized="by">by </word>
    <word normalized="Goldberg">Goldberg</word>
    <word normalized="">, </word>
    <word normalized="Rude">Rude </word>
    <word normalized="and">and </word>
    <word normalized="Hennig">Hennig </word>
    <word normalized="attacked">attacked </word>
    <word normalized="him">him</word>
    <word normalized="">, </word>
    <word normalized="later">later </word>
    <word normalized="joining">joining </word>
    <word normalized="nWo">nWo </word>
    <word normalized="Hollywood">Hollywood</word>
    <word normalized="">, </word>
    <word normalized="the">the </word>
    <word normalized="rivals">rivals </word>
    <word normalized="of">of </word>
    <word normalized="the">the </word>
    <word normalized="Wolfpac">Wolfpac</word>
    <word normalized="">. </word>
  </sentence>
  <sentence>
    <word normalized="By">By </word>
    <word normalized="late">late </word>
    <word normalized="19">19 </word>
    <word normalized="hundred">hundred </word>
    <word normalized="ninety eight">98</word>
    <word normalized="">, </word>
    <word normalized="both">both </word>
    <word normalized="Rude">Rude </word>
    <word normalized="and">and </word>
    <word normalized="Hennig">Hennig </word>
    <word normalized="were">were </word>
    <word normalized="off">off </word>
    <word normalized="W C W">WCW </word>
    <word normalized="T V">TV </word>
    <word normalized="due">due </word>
    <word normalized="to">to </word>
    <word normalized="injuries">injuries</word>
    <word normalized="">. </word>
  </sentence>
  <sentence>
    <word normalized="Hennig">Hennig </word>
    <word normalized="had">had </word>
    <word normalized="an">an </word>
    <word normalized="ongoing">ongoing </word>
    <word normalized="leg">leg </word>
    <word normalized="injury">injury </word>
    <word normalized="that">that </word>
    <word normalized="year">year</word>
    <word normalized="">, </word>
    <word normalized="and">and </word>
    <word normalized="Rude">Rude </word>
    <word normalized="was">was </word>
    <word normalized="thought">thought </word>
    <word normalized="to">to </word>
    <word normalized="have">have </word>
    <word normalized="had">had </word>
    <word normalized="testicular">testicular </word>
    <word normalized="cancer">cancer </word>
    <word normalized="which">which </word>
    <word normalized="later">later </word>
    <word normalized="turned">turned </word>
    <word normalized="out">out </word>
    <word normalized="to">to </word>
    <word normalized="be">be </word>
    <word normalized="a">a </word>
    <word normalized="cyst">cyst</word>
    <word normalized="">. </word>
  </sentence>
  <sentence>
    <word normalized="Curt">Curt </word>
    <word normalized="Hennig">Hennig </word>
    <word normalized="returned">returned </word>
    <word normalized="to">to </word>
    <word normalized="the">the </word>
    <word normalized="nWo">nWo </word>
    <word normalized="from">from </word>
    <word normalized="his">his </word>
    <word normalized="injury">injury </word>
    <word normalized="at">at </word>
    <word normalized="Starrcade">Starrcade </word>
    <word normalized="nineteen">19 </word>
    <word normalized="hundred">hundred </word>
    <word normalized="ninety eight">98 </word>
    <word normalized="without">without </word>
    <word normalized="Rude">Rude</word>
    <word normalized="">, </word>
    <word normalized="who">who </word>
    <word normalized="was">was </word>
    <word normalized="still">still </word>
    <word normalized="unable">unable </word>
    <word normalized="to">to </word>
    <word normalized="appear">appear </word>
    <word normalized="on">on </word>
    <word normalized="W C W">WCW</word>
    <word normalized="">. </word>
  </sentence>
  <sentence>
    <word normalized="Rude">Rude </word>
    <word normalized="was">was </word>
    <word normalized="rumored">rumored </word>
    <word normalized="to">to </word>
    <word normalized="be">be </word>
    <word normalized="training">training </word>
    <word normalized="for">for </word>
    <word normalized="a">a </word>
    <word normalized="full">full </word>
    <word normalized="time">time </word>
    <word normalized="comeback">comeback </word>
    <word normalized="to">to </word>
    <word normalized="active">active </word>
    <word normalized="wrestling">wrestling </word>
    <word normalized="in">in </word>
    <word normalized="early">early </word>
    <word normalized="nineteen">19 </word>
    <word normalized="hundred">hundred </word>
    <word normalized="ninety nine">99</word>
    <word normalized="">. </word>
  </sentence>
  <sentence>
    <word normalized="Section">Section </word>
    <word normalized="two">2 </word>
    <word normalized="Death">Death </word>
    <word normalized="Rude">Rude </word>
    <word normalized="died">died </word>
    <word normalized="on">on </word>
    <word normalized="April">April </word>
    <word normalized="twenty">20 </word>
    <word normalized="nineteen">19 </word>
    <word normalized="hundred">hundred </word>
    <word normalized="ninety nine">99 </word>
    <word normalized="after">after </word>
    <word normalized="suffering">suffering </word>
    <word normalized="heart">heart </word>
    <word normalized="failure">failure</word>
    <word normalized="">. </word>
  </sentence>
  <sentence>
    <word normalized="He">He </word>
    <word normalized="is">is </word>
    <word normalized="survived">survived </word>
    <word normalized="by">by </word>
    <word normalized="his">his </word>
    <word normalized="wife">wife</word>
    <word normalized="">, </word>
    <word normalized="Michelle">Michelle </word>
    <word normalized="and">and </word>
    <word normalized="their">their </word>
    <word normalized="three">three </word>
    <word normalized="children">children</word>
    <word normalized="">. </word>
  </sentence>
  <sentence>
    <word normalized="The">The </word>
    <word normalized="believed">believed </word>
    <word normalized="cause">cause </word>
    <word normalized="of">of </word>
    <word normalized="death">death </word>
    <word normalized="may">may </word>
    <word normalized="have">have </word>
    <word normalized="been">been </word>
    <word normalized="an">an </word>
    <word normalized="overdose">overdose </word>
    <word normalized="of">of </word>
    <word normalized="Gamma Hydroxybutyric">Gamma-Hydroxybutyric </word>
    <word normalized="acid">acid </word>
    <word normalized="">(</word>
    <word normalized="G H B">GHB</word>
    <word normalized="">) </word>
    <word normalized="and">and </word>
    <word normalized="steroids">steroids</word>
    <word normalized="">. </word>
  </sentence>
  <sentence>
    <word normalized="An">An </word>
    <word normalized="autopsy">autopsy </word>
    <word normalized="report">report </word>
    <word normalized="showed">showed </word>
    <word normalized="he">he </word>
    <word normalized="died">died </word>
    <word normalized="from">from </word>
    <word normalized="an">an </word>
    <word normalized="overdose">overdose </word>
    <word normalized="of">of </word>
    <word normalized="">"</word>
    <word normalized="mixed">mixed </word>
    <word normalized="medications">medications</word>
    <word normalized="">"</word>
    <word normalized="">. </word>
  </sentence>
  <sentence>
    <word normalized="Rude">Rude </word>
    <word normalized="testified">testified </word>
    <word normalized="in">in </word>
    <word normalized="19">19 </word>
    <word normalized="hundred">hundred </word>
    <word normalized="ninety four">94 </word>
    <word normalized="that">that </word>
    <word normalized="he">he </word>
    <word normalized="had">had </word>
    <word normalized="used">used </word>
    <word normalized="anabolic">anabolic </word>
    <word normalized="steroids">steroids </word>
    <word normalized="to">to </word>
    <word normalized="">"</word>
    <word normalized="build">build </word>
    <word normalized="muscle">muscle </word>
    <word normalized="mass">mass </word>
    <word normalized="and">and </word>
    <word normalized="relieve">relieve </word>
    <word normalized="joint">joint </word>
    <word normalized="pain">pain</word>
    <word normalized="">"</word>
    <word normalized="">. </word>
  </sentence>
  <sentence>
    <word normalized="Section">Section </word>
    <word normalized="three">3 </word>
    <word normalized="In">In </word>
    <word normalized="wrestling">wrestling </word>
    <word normalized="Finishing">Finishing </word>
    <word normalized="and">and </word>
    <word normalized="signature">signature </word>
    <word normalized="moves">moves </word>
    <word normalized="Rude">Rude </word>
    <word normalized="Awakening">Awakening </word>
    <word normalized="">(</word>
    <word normalized="Hangman s">Hangman's </word>
    <word normalized="neckbreaker">neckbreaker</word>
    <word normalized="">, </word>
    <word normalized="sometimes">sometimes </word>
    <word normalized="preceded">preceded </word>
    <word normalized="by">by </word>
    <word normalized="his">his </word>
    <word normalized="hip">hip </word>
    <word normalized="swinging">swinging </word>
    <word normalized="taunt">taunt</word>
    <word normalized="">) </word>
    <word normalized="Overhead">Overhead </word>
    <word normalized="gutwrench">gutwrench </word>
    <word normalized="backbreaker">backbreaker </word>
    <word normalized="rack">rack </word>
    <word normalized="Back">Back </word>
    <word normalized="to">to </word>
    <word normalized="belly">belly </word>
    <word normalized="piledriver">piledriver </word>
    <word normalized="Swinging">Swinging </word>
    <word normalized="neckbreaker">neckbreaker </word>
    <word normalized="DDT">DDT </word>
    <word normalized="Figure">Figure </word>
    <word normalized="four">four </word>
    <word normalized="leglock">leglock </word>
    <word normalized="Diving">Diving </word>
    <word normalized="knee">knee </word>
    <word normalized="drop">drop </word>
    <word normalized="Managers">Managers </word>
    <word normalized="Jimmy">Jimmy </word>
    <word normalized="Hart">Hart </word>
    <word normalized="Bobby">Bobby </word>
    <word normalized="Heenan">Heenan </word>
    <word normalized="Paul">Paul </word>
    <word normalized="Jones">Jones </word>
    <word normalized="Percy">Percy </word>
    <word normalized="Pringle">Pringle </word>
    <word normalized="III">III </word>
    <word normalized="Raven">Raven </word>
    <word normalized="">(</word>
    <word normalized="Rude s">Rude's </word>
    <word normalized="sister">sister </word>
    <word normalized="Nancy">Nancy</word>
    <word normalized="">) </word>
    <word normalized="Section">Section </word>
    <word normalized="4">4 </word>
    <word normalized="Championships">Championships </word>
    <word normalized="and">and </word>
    <word normalized="accomplishments">accomplishments </word>
    <word normalized="Championship">Championship </word>
    <word normalized="Wrestling">Wrestling </word>
    <word normalized="from">from </word>
    <word normalized="Florida">Florida </word>
    <word normalized="NWA">NWA </word>
    <word normalized="Florida">Florida </word>
    <word normalized="Southern">Southern </word>
    <word normalized="Heavyweight">Heavyweight </word>
    <word normalized="Championship">Championship </word>
    <word normalized="">(</word>
    <word normalized="two">2 </word>
    <word normalized="times">times</word>
    <word normalized="">) </word>
    <word normalized="NWA">NWA </word>
    <word normalized="Florida">Florida </word>
    <word normalized="United">United </word>
    <word normalized="States">States </word>
    <word normalized="Tag">Tag </word>
    <word normalized="Team">Team </word>
    <word normalized="Championship">Championship </word>
    <word normalized="">(</word>
    <word normalized="1">1 </word>
    <word normalized="time">time</word>
    <word normalized="">) </word>
    <word normalized="">- </word>
    <word normalized="with">with </word>
    <word normalized="Jesse">Jesse </word>
    <word normalized="Barr">Barr </word>
    <word normalized="Continental">Continental </word>
    <word normalized="Wrestling">Wrestling </word>
    <word normalized="Association">Association </word>
    <word normalized="AWA">AWA </word>
    <word normalized="Southern">Southern </word>
    <word normalized="Heavyweight">Heavyweight </word>
    <word normalized="Championship">Championship </word>
    <word normalized="">(</word>
    <word normalized="one">1 </word>
    <word normalized="time">time</word>
    <word normalized="">) </word>
    <word normalized="AWA">AWA </word>
    <word normalized="Southern">Southern </word>
    <word normalized="Tag">Tag </word>
    <word normalized="Team">Team </word>
    <word normalized="Championship">Championship </word>
    <word normalized="">(</word>
    <word normalized="1">1 </word>
    <word normalized="time">time</word>
    <word normalized="">) </word>
    <word normalized="">- </word>
    <word normalized="with">with </word>
    <word normalized="King">King </word>
    <word normalized="Kong">Kong </word>
    <word normalized="Bundy">Bundy </word>
    <word normalized="Jim">Jim </word>
    <word normalized="Crockett">Crockett </word>
    <word normalized="Promotions">Promotions </word>
    <word normalized="">| </word>
    <word normalized="World">World </word>
    <word normalized="Championship">Championship </word>
    <word normalized="Wrestling">Wrestling </word>
    <word normalized="NWA">NWA </word>
    <word normalized="World">World </word>
    <word normalized="Tag">Tag </word>
    <word normalized="Team">Team </word>
    <word normalized="Championship">Championship </word>
    <word normalized="">(</word>
    <word normalized="Mid Atlantic">Mid-Atlantic </word>
    <word normalized="version">version</word>
    <word normalized="">) </word>
    <word normalized="">(</word>
    <word normalized="1">1 </word>
    <word normalized="time">time</word>
    <word normalized="">) </word>
    <word normalized="">- </word>
    <word normalized="with">with </word>
    <word normalized="Manny">Manny </word>
    <word normalized="Fernandez">Fernandez </word>
    <word normalized="W C W">WCW </word>
    <word normalized="International">International </word>
    <word normalized="World">World </word>
    <word normalized="Heavyweight">Heavyweight </word>
    <word normalized="Championship">Championship </word>
    <word normalized="">(</word>
    <word normalized="three">3 </word>
    <word normalized="times">times</word>
    <word normalized="">) </word>
    <word normalized="W C W">WCW </word>
    <word normalized="United">United </word>
    <word normalized="States">States </word>
    <word normalized="Heavyweight">Heavyweight </word>
    <word normalized="Championship">Championship </word>
    <word normalized="">(</word>
    <word normalized="1">1 </word>
    <word normalized="time">time</word>
    <word normalized="">) </word>
    <word normalized="World">World </word>
    <word normalized="Class">Class </word>
    <word normalized="Championship">Championship </word>
    <word normalized="Wrestling">Wrestling </word>
    <word normalized="">| </word>
    <word normalized="World">World </word>
    <word normalized="Class">Class </word>
    <word normalized="Wrestling">Wrestling </word>
    <word normalized="Association">Association </word>
    <word normalized="NWA">NWA </word>
    <word normalized="American">American </word>
    <word normalized="Heavyweight">Heavyweight </word>
    <word normalized="Championship">Championship </word>
    <word normalized="">(</word>
    <word normalized="1">1 </word>
    <word normalized="time">time</word>
    <word normalized="">) </word>
    <word normalized="">(</word>
    <word normalized="Last">Last</word>
    <word normalized="">) </word>
    <word normalized="W C C W">WCCW </word>
    <word normalized="Television">Television </word>
    <word normalized="Championship">Championship </word>
    <word normalized="">(</word>
    <word normalized="1">1 </word>
    <word normalized="time">time</word>
    <word normalized="">) </word>
    <word normalized="WCWA">WCWA </word>
    <word normalized="World">World </word>
    <word normalized="Heavyweight">Heavyweight </word>
    <word normalized="Championship">Championship </word>
    <word normalized="">(</word>
    <word normalized="1">1 </word>
    <word normalized="time">time</word>
    <word normalized="">) </word>
    <word normalized="">(</word>
    <word normalized="First">First</word>
    <word normalized="">) </word>
    <word normalized="World">World </word>
    <word normalized="Wrestling">Wrestling </word>
    <word normalized="Federation">Federation </word>
    <word normalized="W W F">WWF </word>
    <word normalized="Intercontinental">Intercontinental </word>
    <word normalized="Championship">Championship </word>
    <word normalized="">(</word>
    <word normalized="1">1 </word>
    <word normalized="time">time</word>
    <word normalized="">) </word>
    <word normalized="Pro">Pro </word>
    <word normalized="Wrestling">Wrestling </word>
    <word normalized="Illustrated">Illustrated </word>
    <word normalized="PWI">PWI </word>
    <word normalized="Most">Most </word>
    <word normalized="Hated">Hated </word>
    <word normalized="Wrestler">Wrestler </word>
    <word normalized="of">of </word>
    <word normalized="the">the </word>
    <word normalized="Year">Year </word>
    <word normalized="">(</word>
    <word normalized="19">19 </word>
    <word normalized="hundred">hundred </word>
    <word normalized="ninety two">92</word>
    <word normalized="">) </word>
    <word normalized="PWI">PWI </word>
    <word normalized="ranked">ranked </word>
    <word normalized="him">him </word>
    <word normalized="hashtag"># </word>
    <word normalized="57">57 </word>
    <word normalized="of">of </word>
    <word normalized="the">the </word>
    <word normalized="five hundred">500 </word>
    <word normalized="best">best </word>
    <word normalized="singles">singles </word>
    <word normalized="wrestlers">wrestlers </word>
    <word normalized="of">of </word>
    <word normalized="the">the </word>
    <word normalized="PWI">PWI </word>
    <word normalized="Years">Years </word>
    <word normalized="in">in </word>
    <word normalized="two thousand three">2003</word>
    <word normalized="">. </word>
  </sentence>
  <sentence>
    <word normalized="Wrestling">Wrestling </word>
    <word normalized="Observer">Observer </word>
    <word normalized="Newsletter">Newsletter </word>
    <word normalized="awards">awards </word>
    <word normalized="Best">Best </word>
    <word normalized="Heel">Heel </word>
    <word normalized="">(</word>
    <word normalized="nineteen">19 </word>
    <word normalized="hundred">hundred </word>
    <word normalized="ninety two">92</word>
    <word normalized="">) </word>
    <word normalized="Section">Section </word>
    <word normalized="5">5 </word>
    <word normalized="Notes">Notes </word>
    <word normalized="Section">Section </word>
    <word normalized="six">6 </word>
    <word normalized="Further">Further </word>
    <word normalized="reading">reading </word>
    <word normalized="Meltzer">Meltzer</word>
    <word normalized="">, </word>
    <word normalized="Dave">Dave </word>
    <word normalized="">(</word>
    <word normalized="October">October </word>
    <word normalized="two thousand one">2001</word>
    <word normalized="">)</word>
    <word normalized="">. </word>
  </sentence>
  <sentence>
    <word normalized="Tributes">Tributes</word>
    <word normalized="">. </word>
  </sentence>
  <sentence>
    <word normalized="Winding">Winding </word>
    <word normalized="Stair">Stair </word>
    <word normalized="Press">Press</word>
    <word normalized="">. </word>
  </sentence>
  <sentence>
    <word normalized="ISBN">ISBN </word>
    <word normalized="1553660854">1553660854</word>
    <word normalized="">. </word>
  </sentence>
</alignment>
